odoo/addons/l10n_es_facturae_custom_rounding_copy_copy/README.rst
odoo/addons/l10n_es_facturae_custom_rounding_copy_copy/__init__.py
odoo/addons/l10n_es_facturae_custom_rounding_copy_copy/__manifest__.py
odoo/addons/l10n_es_facturae_custom_rounding_copy_copy/models/__init__.py
odoo/addons/l10n_es_facturae_custom_rounding_copy_copy/models/account_move.py
odoo/addons/l10n_es_facturae_custom_rounding_copy_copy/readme/CONFIGURE.md
odoo/addons/l10n_es_facturae_custom_rounding_copy_copy/readme/CONTRIBUTORS.md
odoo/addons/l10n_es_facturae_custom_rounding_copy_copy/readme/DESCRIPTION.md
odoo/addons/l10n_es_facturae_custom_rounding_copy_copy/readme/USAGE.md
odoo/addons/l10n_es_facturae_custom_rounding_copy_copy/static/description/icon.png
odoo/addons/l10n_es_facturae_custom_rounding_copy_copy/static/description/index.html
odoo/addons/l10n_es_facturae_custom_rounding_copy_copy/tests/__init__.py
odoo/addons/l10n_es_facturae_custom_rounding_copy_copy/tests/test_facturae_custom_rounding.py
odoo_addon_l10n_es_facturae_custom_rounding_copy_copy-15.0.1.1.0.dist-info/METADATA
odoo_addon_l10n_es_facturae_custom_rounding_copy_copy-15.0.1.1.0.dist-info/WHEEL
odoo_addon_l10n_es_facturae_custom_rounding_copy_copy-15.0.1.1.0.dist-info/top_level.txt
odoo_addon_l10n_es_facturae_custom_rounding_copy_copy-15.0.1.1.0.dist-info/RECORD
